{
	"name": "102_fbas_07fot2_fbas_07fot2_cuffedboots_00a_red",
	"plugin-id": "Sprite",
	"sid": 908676072203016,
	"isGlobal": false,
	"editorNewInstanceIsReplica": true,
	"instanceVariables": [],
	"behaviorTypes": [],
	"effectTypes": [],
	"animations": {
		"items": [
			{
				"frames": [
					{
						"width": 64,
						"height": 64,
						"originX": 0.5,
						"originY": 0.5,
						"originalSource": "",
						"exportFormat": "lossless",
						"exportQuality": 0.8,
						"fileType": "image/png",
						"imageSpriteId": 1823325,
						"useCollisionPoly": true,
						"duration": 1,
						"tag": ""
					},
					{
						"width": 64,
						"height": 64,
						"originX": 0.5,
						"originY": 0.5,
						"originalSource": "",
						"exportFormat": "lossless",
						"exportQuality": 0.8,
						"fileType": "image/png",
						"imageSpriteId": 1930893,
						"useCollisionPoly": true,
						"duration": 1,
						"tag": ""
					},
					{
						"width": 64,
						"height": 64,
						"originX": 0.5,
						"originY": 0.5,
						"originalSource": "",
						"exportFormat": "lossless",
						"exportQuality": 0.8,
						"fileType": "image/png",
						"imageSpriteId": 6593590,
						"useCollisionPoly": true,
						"duration": 1,
						"tag": ""
					},
					{
						"width": 64,
						"height": 64,
						"originX": 0.5,
						"originY": 0.5,
						"originalSource": "",
						"exportFormat": "lossless",
						"exportQuality": 0.8,
						"fileType": "image/png",
						"imageSpriteId": 1686959,
						"useCollisionPoly": true,
						"duration": 1,
						"tag": ""
					},
					{
						"width": 64,
						"height": 64,
						"originX": 0.5,
						"originY": 0.5,
						"originalSource": "",
						"exportFormat": "lossless",
						"exportQuality": 0.8,
						"fileType": "image/png",
						"imageSpriteId": 4188726,
						"useCollisionPoly": true,
						"duration": 1,
						"tag": ""
					},
					{
						"width": 64,
						"height": 64,
						"originX": 0.5,
						"originY": 0.5,
						"originalSource": "",
						"exportFormat": "lossless",
						"exportQuality": 0.8,
						"fileType": "image/png",
						"imageSpriteId": 8728721,
						"useCollisionPoly": true,
						"duration": 1,
						"tag": ""
					},
					{
						"width": 64,
						"height": 64,
						"originX": 0.5,
						"originY": 0.5,
						"originalSource": "",
						"exportFormat": "lossless",
						"exportQuality": 0.8,
						"fileType": "image/png",
						"imageSpriteId": 6754862,
						"useCollisionPoly": true,
						"duration": 1,
						"tag": ""
					},
					{
						"width": 64,
						"height": 64,
						"originX": 0.5,
						"originY": 0.5,
						"originalSource": "",
						"exportFormat": "lossless",
						"exportQuality": 0.8,
						"fileType": "image/png",
						"imageSpriteId": 7024305,
						"useCollisionPoly": true,
						"duration": 1,
						"tag": ""
					},
					{
						"width": 64,
						"height": 64,
						"originX": 0.5,
						"originY": 0.5,
						"originalSource": "",
						"exportFormat": "lossless",
						"exportQuality": 0.8,
						"fileType": "image/png",
						"imageSpriteId": 6140501,
						"useCollisionPoly": true,
						"duration": 1,
						"tag": ""
					},
					{
						"width": 64,
						"height": 64,
						"originX": 0.5,
						"originY": 0.5,
						"originalSource": "",
						"exportFormat": "lossless",
						"exportQuality": 0.8,
						"fileType": "image/png",
						"imageSpriteId": 1013120,
						"useCollisionPoly": true,
						"duration": 1,
						"tag": ""
					},
					{
						"width": 64,
						"height": 64,
						"originX": 0.5,
						"originY": 0.5,
						"originalSource": "",
						"exportFormat": "lossless",
						"exportQuality": 0.8,
						"fileType": "image/png",
						"imageSpriteId": 1646507,
						"useCollisionPoly": true,
						"duration": 1,
						"tag": ""
					},
					{
						"width": 64,
						"height": 64,
						"originX": 0.5,
						"originY": 0.5,
						"originalSource": "",
						"exportFormat": "lossless",
						"exportQuality": 0.8,
						"fileType": "image/png",
						"imageSpriteId": 2884771,
						"useCollisionPoly": true,
						"duration": 1,
						"tag": ""
					},
					{
						"width": 64,
						"height": 64,
						"originX": 0.5,
						"originY": 0.5,
						"originalSource": "",
						"exportFormat": "lossless",
						"exportQuality": 0.8,
						"fileType": "image/png",
						"imageSpriteId": 2049403,
						"useCollisionPoly": true,
						"duration": 1,
						"tag": ""
					},
					{
						"width": 64,
						"height": 64,
						"originX": 0.5,
						"originY": 0.5,
						"originalSource": "",
						"exportFormat": "lossless",
						"exportQuality": 0.8,
						"fileType": "image/png",
						"imageSpriteId": 2216301,
						"useCollisionPoly": true,
						"duration": 1,
						"tag": ""
					},
					{
						"width": 64,
						"height": 64,
						"originX": 0.5,
						"originY": 0.5,
						"originalSource": "",
						"exportFormat": "lossless",
						"exportQuality": 0.8,
						"fileType": "image/png",
						"imageSpriteId": 1037934,
						"useCollisionPoly": true,
						"duration": 1,
						"tag": ""
					},
					{
						"width": 64,
						"height": 64,
						"originX": 0.5,
						"originY": 0.5,
						"originalSource": "",
						"exportFormat": "lossless",
						"exportQuality": 0.8,
						"fileType": "image/png",
						"imageSpriteId": 3086415,
						"useCollisionPoly": true,
						"duration": 1,
						"tag": ""
					},
					{
						"width": 64,
						"height": 64,
						"originX": 0.5,
						"originY": 0.5,
						"originalSource": "",
						"exportFormat": "lossless",
						"exportQuality": 0.8,
						"fileType": "image/png",
						"imageSpriteId": 249903,
						"useCollisionPoly": true,
						"duration": 1,
						"tag": ""
					},
					{
						"width": 64,
						"height": 64,
						"originX": 0.5,
						"originY": 0.5,
						"originalSource": "",
						"exportFormat": "lossless",
						"exportQuality": 0.8,
						"fileType": "image/png",
						"imageSpriteId": 5012891,
						"useCollisionPoly": true,
						"duration": 1,
						"tag": ""
					},
					{
						"width": 64,
						"height": 64,
						"originX": 0.5,
						"originY": 0.5,
						"originalSource": "",
						"exportFormat": "lossless",
						"exportQuality": 0.8,
						"fileType": "image/png",
						"imageSpriteId": 8018169,
						"useCollisionPoly": true,
						"duration": 1,
						"tag": ""
					},
					{
						"width": 64,
						"height": 64,
						"originX": 0.5,
						"originY": 0.5,
						"originalSource": "",
						"exportFormat": "lossless",
						"exportQuality": 0.8,
						"fileType": "image/png",
						"imageSpriteId": 9089498,
						"useCollisionPoly": true,
						"duration": 1,
						"tag": ""
					},
					{
						"width": 64,
						"height": 64,
						"originX": 0.5,
						"originY": 0.5,
						"originalSource": "",
						"exportFormat": "lossless",
						"exportQuality": 0.8,
						"fileType": "image/png",
						"imageSpriteId": 2232046,
						"useCollisionPoly": true,
						"duration": 1,
						"tag": ""
					},
					{
						"width": 64,
						"height": 64,
						"originX": 0.5,
						"originY": 0.5,
						"originalSource": "",
						"exportFormat": "lossless",
						"exportQuality": 0.8,
						"fileType": "image/png",
						"imageSpriteId": 9230946,
						"useCollisionPoly": true,
						"duration": 1,
						"tag": ""
					},
					{
						"width": 64,
						"height": 64,
						"originX": 0.5,
						"originY": 0.5,
						"originalSource": "",
						"exportFormat": "lossless",
						"exportQuality": 0.8,
						"fileType": "image/png",
						"imageSpriteId": 6849480,
						"useCollisionPoly": true,
						"duration": 1,
						"tag": ""
					},
					{
						"width": 64,
						"height": 64,
						"originX": 0.5,
						"originY": 0.5,
						"originalSource": "",
						"exportFormat": "lossless",
						"exportQuality": 0.8,
						"fileType": "image/png",
						"imageSpriteId": 4484477,
						"useCollisionPoly": true,
						"duration": 1,
						"tag": ""
					},
					{
						"width": 64,
						"height": 64,
						"originX": 0.5,
						"originY": 0.5,
						"originalSource": "",
						"exportFormat": "lossless",
						"exportQuality": 0.8,
						"fileType": "image/png",
						"imageSpriteId": 8494046,
						"useCollisionPoly": true,
						"duration": 1,
						"tag": ""
					},
					{
						"width": 64,
						"height": 64,
						"originX": 0.5,
						"originY": 0.5,
						"originalSource": "",
						"exportFormat": "lossless",
						"exportQuality": 0.8,
						"fileType": "image/png",
						"imageSpriteId": 7486686,
						"useCollisionPoly": true,
						"duration": 1,
						"tag": ""
					},
					{
						"width": 64,
						"height": 64,
						"originX": 0.5,
						"originY": 0.5,
						"originalSource": "",
						"exportFormat": "lossless",
						"exportQuality": 0.8,
						"fileType": "image/png",
						"imageSpriteId": 5102075,
						"useCollisionPoly": true,
						"duration": 1,
						"tag": ""
					},
					{
						"width": 64,
						"height": 64,
						"originX": 0.5,
						"originY": 0.5,
						"originalSource": "",
						"exportFormat": "lossless",
						"exportQuality": 0.8,
						"fileType": "image/png",
						"imageSpriteId": 1230094,
						"useCollisionPoly": true,
						"duration": 1,
						"tag": ""
					},
					{
						"width": 64,
						"height": 64,
						"originX": 0.5,
						"originY": 0.5,
						"originalSource": "",
						"exportFormat": "lossless",
						"exportQuality": 0.8,
						"fileType": "image/png",
						"imageSpriteId": 8992836,
						"useCollisionPoly": true,
						"duration": 1,
						"tag": ""
					},
					{
						"width": 64,
						"height": 64,
						"originX": 0.5,
						"originY": 0.5,
						"originalSource": "",
						"exportFormat": "lossless",
						"exportQuality": 0.8,
						"fileType": "image/png",
						"imageSpriteId": 8351227,
						"useCollisionPoly": true,
						"duration": 1,
						"tag": ""
					},
					{
						"width": 64,
						"height": 64,
						"originX": 0.5,
						"originY": 0.5,
						"originalSource": "",
						"exportFormat": "lossless",
						"exportQuality": 0.8,
						"fileType": "image/png",
						"imageSpriteId": 2933909,
						"useCollisionPoly": true,
						"duration": 1,
						"tag": ""
					},
					{
						"width": 64,
						"height": 64,
						"originX": 0.5,
						"originY": 0.5,
						"originalSource": "",
						"exportFormat": "lossless",
						"exportQuality": 0.8,
						"fileType": "image/png",
						"imageSpriteId": 6102440,
						"useCollisionPoly": true,
						"duration": 1,
						"tag": ""
					},
					{
						"width": 64,
						"height": 64,
						"originX": 0.5,
						"originY": 0.5,
						"originalSource": "",
						"exportFormat": "lossless",
						"exportQuality": 0.8,
						"fileType": "image/png",
						"imageSpriteId": 5696246,
						"useCollisionPoly": true,
						"duration": 1,
						"tag": ""
					},
					{
						"width": 64,
						"height": 64,
						"originX": 0.5,
						"originY": 0.5,
						"originalSource": "",
						"exportFormat": "lossless",
						"exportQuality": 0.8,
						"fileType": "image/png",
						"imageSpriteId": 4461677,
						"useCollisionPoly": true,
						"duration": 1,
						"tag": ""
					},
					{
						"width": 64,
						"height": 64,
						"originX": 0.5,
						"originY": 0.5,
						"originalSource": "",
						"exportFormat": "lossless",
						"exportQuality": 0.8,
						"fileType": "image/png",
						"imageSpriteId": 4067191,
						"useCollisionPoly": true,
						"duration": 1,
						"tag": ""
					},
					{
						"width": 64,
						"height": 64,
						"originX": 0.5,
						"originY": 0.5,
						"originalSource": "",
						"exportFormat": "lossless",
						"exportQuality": 0.8,
						"fileType": "image/png",
						"imageSpriteId": 5409591,
						"useCollisionPoly": true,
						"duration": 1,
						"tag": ""
					},
					{
						"width": 64,
						"height": 64,
						"originX": 0.5,
						"originY": 0.5,
						"originalSource": "",
						"exportFormat": "lossless",
						"exportQuality": 0.8,
						"fileType": "image/png",
						"imageSpriteId": 9360827,
						"useCollisionPoly": true,
						"duration": 1,
						"tag": ""
					},
					{
						"width": 64,
						"height": 64,
						"originX": 0.5,
						"originY": 0.5,
						"originalSource": "",
						"exportFormat": "lossless",
						"exportQuality": 0.8,
						"fileType": "image/png",
						"imageSpriteId": 6402512,
						"useCollisionPoly": true,
						"duration": 1,
						"tag": ""
					},
					{
						"width": 64,
						"height": 64,
						"originX": 0.5,
						"originY": 0.5,
						"originalSource": "",
						"exportFormat": "lossless",
						"exportQuality": 0.8,
						"fileType": "image/png",
						"imageSpriteId": 7455009,
						"useCollisionPoly": true,
						"duration": 1,
						"tag": ""
					},
					{
						"width": 64,
						"height": 64,
						"originX": 0.5,
						"originY": 0.5,
						"originalSource": "",
						"exportFormat": "lossless",
						"exportQuality": 0.8,
						"fileType": "image/png",
						"imageSpriteId": 34986,
						"useCollisionPoly": true,
						"duration": 1,
						"tag": ""
					},
					{
						"width": 64,
						"height": 64,
						"originX": 0.5,
						"originY": 0.5,
						"originalSource": "",
						"exportFormat": "lossless",
						"exportQuality": 0.8,
						"fileType": "image/png",
						"imageSpriteId": 6940756,
						"useCollisionPoly": true,
						"duration": 1,
						"tag": ""
					},
					{
						"width": 64,
						"height": 64,
						"originX": 0.5,
						"originY": 0.5,
						"originalSource": "",
						"exportFormat": "lossless",
						"exportQuality": 0.8,
						"fileType": "image/png",
						"imageSpriteId": 7283885,
						"useCollisionPoly": true,
						"duration": 1,
						"tag": ""
					},
					{
						"width": 64,
						"height": 64,
						"originX": 0.5,
						"originY": 0.5,
						"originalSource": "",
						"exportFormat": "lossless",
						"exportQuality": 0.8,
						"fileType": "image/png",
						"imageSpriteId": 6624489,
						"useCollisionPoly": true,
						"duration": 1,
						"tag": ""
					},
					{
						"width": 64,
						"height": 64,
						"originX": 0.5,
						"originY": 0.5,
						"originalSource": "",
						"exportFormat": "lossless",
						"exportQuality": 0.8,
						"fileType": "image/png",
						"imageSpriteId": 1728694,
						"useCollisionPoly": true,
						"duration": 1,
						"tag": ""
					},
					{
						"width": 64,
						"height": 64,
						"originX": 0.5,
						"originY": 0.5,
						"originalSource": "",
						"exportFormat": "lossless",
						"exportQuality": 0.8,
						"fileType": "image/png",
						"imageSpriteId": 3722593,
						"useCollisionPoly": true,
						"duration": 1,
						"tag": ""
					},
					{
						"width": 64,
						"height": 64,
						"originX": 0.5,
						"originY": 0.5,
						"originalSource": "",
						"exportFormat": "lossless",
						"exportQuality": 0.8,
						"fileType": "image/png",
						"imageSpriteId": 4358976,
						"useCollisionPoly": true,
						"duration": 1,
						"tag": ""
					},
					{
						"width": 64,
						"height": 64,
						"originX": 0.5,
						"originY": 0.5,
						"originalSource": "",
						"exportFormat": "lossless",
						"exportQuality": 0.8,
						"fileType": "image/png",
						"imageSpriteId": 9442793,
						"useCollisionPoly": true,
						"duration": 1,
						"tag": ""
					},
					{
						"width": 64,
						"height": 64,
						"originX": 0.5,
						"originY": 0.5,
						"originalSource": "",
						"exportFormat": "lossless",
						"exportQuality": 0.8,
						"fileType": "image/png",
						"imageSpriteId": 5571844,
						"useCollisionPoly": true,
						"duration": 1,
						"tag": ""
					},
					{
						"width": 64,
						"height": 64,
						"originX": 0.5,
						"originY": 0.5,
						"originalSource": "",
						"exportFormat": "lossless",
						"exportQuality": 0.8,
						"fileType": "image/png",
						"imageSpriteId": 2240308,
						"useCollisionPoly": true,
						"duration": 1,
						"tag": ""
					},
					{
						"width": 64,
						"height": 64,
						"originX": 0.5,
						"originY": 0.5,
						"originalSource": "",
						"exportFormat": "lossless",
						"exportQuality": 0.8,
						"fileType": "image/png",
						"imageSpriteId": 8944901,
						"useCollisionPoly": true,
						"duration": 1,
						"tag": ""
					},
					{
						"width": 64,
						"height": 64,
						"originX": 0.5,
						"originY": 0.5,
						"originalSource": "",
						"exportFormat": "lossless",
						"exportQuality": 0.8,
						"fileType": "image/png",
						"imageSpriteId": 7312836,
						"useCollisionPoly": true,
						"duration": 1,
						"tag": ""
					},
					{
						"width": 64,
						"height": 64,
						"originX": 0.5,
						"originY": 0.5,
						"originalSource": "",
						"exportFormat": "lossless",
						"exportQuality": 0.8,
						"fileType": "image/png",
						"imageSpriteId": 2230871,
						"useCollisionPoly": true,
						"duration": 1,
						"tag": ""
					},
					{
						"width": 64,
						"height": 64,
						"originX": 0.5,
						"originY": 0.5,
						"originalSource": "",
						"exportFormat": "lossless",
						"exportQuality": 0.8,
						"fileType": "image/png",
						"imageSpriteId": 1061837,
						"useCollisionPoly": true,
						"duration": 1,
						"tag": ""
					},
					{
						"width": 64,
						"height": 64,
						"originX": 0.5,
						"originY": 0.5,
						"originalSource": "",
						"exportFormat": "lossless",
						"exportQuality": 0.8,
						"fileType": "image/png",
						"imageSpriteId": 2264425,
						"useCollisionPoly": true,
						"duration": 1,
						"tag": ""
					},
					{
						"width": 64,
						"height": 64,
						"originX": 0.5,
						"originY": 0.5,
						"originalSource": "",
						"exportFormat": "lossless",
						"exportQuality": 0.8,
						"fileType": "image/png",
						"imageSpriteId": 1733780,
						"useCollisionPoly": true,
						"duration": 1,
						"tag": ""
					},
					{
						"width": 64,
						"height": 64,
						"originX": 0.5,
						"originY": 0.5,
						"originalSource": "",
						"exportFormat": "lossless",
						"exportQuality": 0.8,
						"fileType": "image/png",
						"imageSpriteId": 4517981,
						"useCollisionPoly": true,
						"duration": 1,
						"tag": ""
					},
					{
						"width": 64,
						"height": 64,
						"originX": 0.5,
						"originY": 0.5,
						"originalSource": "",
						"exportFormat": "lossless",
						"exportQuality": 0.8,
						"fileType": "image/png",
						"imageSpriteId": 7052444,
						"useCollisionPoly": true,
						"duration": 1,
						"tag": ""
					},
					{
						"width": 64,
						"height": 64,
						"originX": 0.5,
						"originY": 0.5,
						"originalSource": "",
						"exportFormat": "lossless",
						"exportQuality": 0.8,
						"fileType": "image/png",
						"imageSpriteId": 8903070,
						"useCollisionPoly": true,
						"duration": 1,
						"tag": ""
					},
					{
						"width": 64,
						"height": 64,
						"originX": 0.5,
						"originY": 0.5,
						"originalSource": "",
						"exportFormat": "lossless",
						"exportQuality": 0.8,
						"fileType": "image/png",
						"imageSpriteId": 1800884,
						"useCollisionPoly": true,
						"duration": 1,
						"tag": ""
					},
					{
						"width": 64,
						"height": 64,
						"originX": 0.5,
						"originY": 0.5,
						"originalSource": "",
						"exportFormat": "lossless",
						"exportQuality": 0.8,
						"fileType": "image/png",
						"imageSpriteId": 371327,
						"useCollisionPoly": true,
						"duration": 1,
						"tag": ""
					},
					{
						"width": 64,
						"height": 64,
						"originX": 0.5,
						"originY": 0.5,
						"originalSource": "",
						"exportFormat": "lossless",
						"exportQuality": 0.8,
						"fileType": "image/png",
						"imageSpriteId": 3254086,
						"useCollisionPoly": true,
						"duration": 1,
						"tag": ""
					},
					{
						"width": 64,
						"height": 64,
						"originX": 0.5,
						"originY": 0.5,
						"originalSource": "",
						"exportFormat": "lossless",
						"exportQuality": 0.8,
						"fileType": "image/png",
						"imageSpriteId": 9683229,
						"useCollisionPoly": true,
						"duration": 1,
						"tag": ""
					},
					{
						"width": 64,
						"height": 64,
						"originX": 0.5,
						"originY": 0.5,
						"originalSource": "",
						"exportFormat": "lossless",
						"exportQuality": 0.8,
						"fileType": "image/png",
						"imageSpriteId": 5863208,
						"useCollisionPoly": true,
						"duration": 1,
						"tag": ""
					},
					{
						"width": 64,
						"height": 64,
						"originX": 0.5,
						"originY": 0.5,
						"originalSource": "",
						"exportFormat": "lossless",
						"exportQuality": 0.8,
						"fileType": "image/png",
						"imageSpriteId": 5546407,
						"useCollisionPoly": true,
						"duration": 1,
						"tag": ""
					},
					{
						"width": 64,
						"height": 64,
						"originX": 0.5,
						"originY": 0.5,
						"originalSource": "",
						"exportFormat": "lossless",
						"exportQuality": 0.8,
						"fileType": "image/png",
						"imageSpriteId": 9530798,
						"useCollisionPoly": true,
						"duration": 1,
						"tag": ""
					},
					{
						"width": 64,
						"height": 64,
						"originX": 0.5,
						"originY": 0.5,
						"originalSource": "",
						"exportFormat": "lossless",
						"exportQuality": 0.8,
						"fileType": "image/png",
						"imageSpriteId": 7220723,
						"useCollisionPoly": true,
						"duration": 1,
						"tag": ""
					},
					{
						"width": 64,
						"height": 64,
						"originX": 0.5,
						"originY": 0.5,
						"originalSource": "",
						"exportFormat": "lossless",
						"exportQuality": 0.8,
						"fileType": "image/png",
						"imageSpriteId": 1358472,
						"useCollisionPoly": true,
						"duration": 1,
						"tag": ""
					},
					{
						"width": 64,
						"height": 64,
						"originX": 0.5,
						"originY": 0.5,
						"originalSource": "",
						"exportFormat": "lossless",
						"exportQuality": 0.8,
						"fileType": "image/png",
						"imageSpriteId": 6297055,
						"useCollisionPoly": true,
						"duration": 1,
						"tag": ""
					},
					{
						"width": 64,
						"height": 64,
						"originX": 0.5,
						"originY": 0.5,
						"originalSource": "",
						"exportFormat": "lossless",
						"exportQuality": 0.8,
						"fileType": "image/png",
						"imageSpriteId": 3747489,
						"useCollisionPoly": true,
						"duration": 1,
						"tag": ""
					},
					{
						"width": 64,
						"height": 64,
						"originX": 0.5,
						"originY": 0.5,
						"originalSource": "",
						"exportFormat": "lossless",
						"exportQuality": 0.8,
						"fileType": "image/png",
						"imageSpriteId": 5844917,
						"useCollisionPoly": true,
						"duration": 1,
						"tag": ""
					},
					{
						"width": 64,
						"height": 64,
						"originX": 0.5,
						"originY": 0.5,
						"originalSource": "",
						"exportFormat": "lossless",
						"exportQuality": 0.8,
						"fileType": "image/png",
						"imageSpriteId": 4491888,
						"useCollisionPoly": true,
						"duration": 1,
						"tag": ""
					},
					{
						"width": 64,
						"height": 64,
						"originX": 0.5,
						"originY": 0.5,
						"originalSource": "",
						"exportFormat": "lossless",
						"exportQuality": 0.8,
						"fileType": "image/png",
						"imageSpriteId": 7246655,
						"useCollisionPoly": true,
						"duration": 1,
						"tag": ""
					},
					{
						"width": 64,
						"height": 64,
						"originX": 0.5,
						"originY": 0.5,
						"originalSource": "",
						"exportFormat": "lossless",
						"exportQuality": 0.8,
						"fileType": "image/png",
						"imageSpriteId": 4118068,
						"useCollisionPoly": true,
						"duration": 1,
						"tag": ""
					},
					{
						"width": 64,
						"height": 64,
						"originX": 0.5,
						"originY": 0.5,
						"originalSource": "",
						"exportFormat": "lossless",
						"exportQuality": 0.8,
						"fileType": "image/png",
						"imageSpriteId": 3187734,
						"useCollisionPoly": true,
						"duration": 1,
						"tag": ""
					},
					{
						"width": 64,
						"height": 64,
						"originX": 0.5,
						"originY": 0.5,
						"originalSource": "",
						"exportFormat": "lossless",
						"exportQuality": 0.8,
						"fileType": "image/png",
						"imageSpriteId": 4633204,
						"useCollisionPoly": true,
						"duration": 1,
						"tag": ""
					},
					{
						"width": 64,
						"height": 64,
						"originX": 0.5,
						"originY": 0.5,
						"originalSource": "",
						"exportFormat": "lossless",
						"exportQuality": 0.8,
						"fileType": "image/png",
						"imageSpriteId": 4951521,
						"useCollisionPoly": true,
						"duration": 1,
						"tag": ""
					},
					{
						"width": 64,
						"height": 64,
						"originX": 0.5,
						"originY": 0.5,
						"originalSource": "",
						"exportFormat": "lossless",
						"exportQuality": 0.8,
						"fileType": "image/png",
						"imageSpriteId": 2427764,
						"useCollisionPoly": true,
						"duration": 1,
						"tag": ""
					},
					{
						"width": 64,
						"height": 64,
						"originX": 0.5,
						"originY": 0.5,
						"originalSource": "",
						"exportFormat": "lossless",
						"exportQuality": 0.8,
						"fileType": "image/png",
						"imageSpriteId": 8247408,
						"useCollisionPoly": true,
						"duration": 1,
						"tag": ""
					},
					{
						"width": 64,
						"height": 64,
						"originX": 0.5,
						"originY": 0.5,
						"originalSource": "",
						"exportFormat": "lossless",
						"exportQuality": 0.8,
						"fileType": "image/png",
						"imageSpriteId": 2603439,
						"useCollisionPoly": true,
						"duration": 1,
						"tag": ""
					},
					{
						"width": 64,
						"height": 64,
						"originX": 0.5,
						"originY": 0.5,
						"originalSource": "",
						"exportFormat": "lossless",
						"exportQuality": 0.8,
						"fileType": "image/png",
						"imageSpriteId": 6570747,
						"useCollisionPoly": true,
						"duration": 1,
						"tag": ""
					},
					{
						"width": 64,
						"height": 64,
						"originX": 0.5,
						"originY": 0.5,
						"originalSource": "",
						"exportFormat": "lossless",
						"exportQuality": 0.8,
						"fileType": "image/png",
						"imageSpriteId": 971361,
						"useCollisionPoly": true,
						"duration": 1,
						"tag": ""
					},
					{
						"width": 64,
						"height": 64,
						"originX": 0.5,
						"originY": 0.5,
						"originalSource": "",
						"exportFormat": "lossless",
						"exportQuality": 0.8,
						"fileType": "image/png",
						"imageSpriteId": 7254476,
						"useCollisionPoly": true,
						"duration": 1,
						"tag": ""
					},
					{
						"width": 64,
						"height": 64,
						"originX": 0.5,
						"originY": 0.5,
						"originalSource": "",
						"exportFormat": "lossless",
						"exportQuality": 0.8,
						"fileType": "image/png",
						"imageSpriteId": 9487838,
						"useCollisionPoly": true,
						"duration": 1,
						"tag": ""
					},
					{
						"width": 64,
						"height": 64,
						"originX": 0.5,
						"originY": 0.5,
						"originalSource": "",
						"exportFormat": "lossless",
						"exportQuality": 0.8,
						"fileType": "image/png",
						"imageSpriteId": 9194760,
						"useCollisionPoly": true,
						"duration": 1,
						"tag": ""
					},
					{
						"width": 64,
						"height": 64,
						"originX": 0.5,
						"originY": 0.5,
						"originalSource": "",
						"exportFormat": "lossless",
						"exportQuality": 0.8,
						"fileType": "image/png",
						"imageSpriteId": 6201607,
						"useCollisionPoly": true,
						"duration": 1,
						"tag": ""
					},
					{
						"width": 64,
						"height": 64,
						"originX": 0.5,
						"originY": 0.5,
						"originalSource": "",
						"exportFormat": "lossless",
						"exportQuality": 0.8,
						"fileType": "image/png",
						"imageSpriteId": 8431096,
						"useCollisionPoly": true,
						"duration": 1,
						"tag": ""
					},
					{
						"width": 64,
						"height": 64,
						"originX": 0.5,
						"originY": 0.5,
						"originalSource": "",
						"exportFormat": "lossless",
						"exportQuality": 0.8,
						"fileType": "image/png",
						"imageSpriteId": 4240731,
						"useCollisionPoly": true,
						"duration": 1,
						"tag": ""
					},
					{
						"width": 64,
						"height": 64,
						"originX": 0.5,
						"originY": 0.5,
						"originalSource": "",
						"exportFormat": "lossless",
						"exportQuality": 0.8,
						"fileType": "image/png",
						"imageSpriteId": 6944212,
						"useCollisionPoly": true,
						"duration": 1,
						"tag": ""
					},
					{
						"width": 64,
						"height": 64,
						"originX": 0.5,
						"originY": 0.5,
						"originalSource": "",
						"exportFormat": "lossless",
						"exportQuality": 0.8,
						"fileType": "image/png",
						"imageSpriteId": 8589145,
						"useCollisionPoly": true,
						"duration": 1,
						"tag": ""
					},
					{
						"width": 64,
						"height": 64,
						"originX": 0.5,
						"originY": 0.5,
						"originalSource": "",
						"exportFormat": "lossless",
						"exportQuality": 0.8,
						"fileType": "image/png",
						"imageSpriteId": 3392458,
						"useCollisionPoly": true,
						"duration": 1,
						"tag": ""
					},
					{
						"width": 64,
						"height": 64,
						"originX": 0.5,
						"originY": 0.5,
						"originalSource": "",
						"exportFormat": "lossless",
						"exportQuality": 0.8,
						"fileType": "image/png",
						"imageSpriteId": 3390850,
						"useCollisionPoly": true,
						"duration": 1,
						"tag": ""
					},
					{
						"width": 64,
						"height": 64,
						"originX": 0.5,
						"originY": 0.5,
						"originalSource": "",
						"exportFormat": "lossless",
						"exportQuality": 0.8,
						"fileType": "image/png",
						"imageSpriteId": 466649,
						"useCollisionPoly": true,
						"duration": 1,
						"tag": ""
					},
					{
						"width": 64,
						"height": 64,
						"originX": 0.5,
						"originY": 0.5,
						"originalSource": "",
						"exportFormat": "lossless",
						"exportQuality": 0.8,
						"fileType": "image/png",
						"imageSpriteId": 4388661,
						"useCollisionPoly": true,
						"duration": 1,
						"tag": ""
					},
					{
						"width": 64,
						"height": 64,
						"originX": 0.5,
						"originY": 0.5,
						"originalSource": "",
						"exportFormat": "lossless",
						"exportQuality": 0.8,
						"fileType": "image/png",
						"imageSpriteId": 4896409,
						"useCollisionPoly": true,
						"duration": 1,
						"tag": ""
					},
					{
						"width": 64,
						"height": 64,
						"originX": 0.5,
						"originY": 0.5,
						"originalSource": "",
						"exportFormat": "lossless",
						"exportQuality": 0.8,
						"fileType": "image/png",
						"imageSpriteId": 1582764,
						"useCollisionPoly": true,
						"duration": 1,
						"tag": ""
					},
					{
						"width": 64,
						"height": 64,
						"originX": 0.5,
						"originY": 0.5,
						"originalSource": "",
						"exportFormat": "lossless",
						"exportQuality": 0.8,
						"fileType": "image/png",
						"imageSpriteId": 5324690,
						"useCollisionPoly": true,
						"duration": 1,
						"tag": ""
					},
					{
						"width": 64,
						"height": 64,
						"originX": 0.5,
						"originY": 0.5,
						"originalSource": "",
						"exportFormat": "lossless",
						"exportQuality": 0.8,
						"fileType": "image/png",
						"imageSpriteId": 3274621,
						"useCollisionPoly": true,
						"duration": 1,
						"tag": ""
					},
					{
						"width": 64,
						"height": 64,
						"originX": 0.5,
						"originY": 0.5,
						"originalSource": "",
						"exportFormat": "lossless",
						"exportQuality": 0.8,
						"fileType": "image/png",
						"imageSpriteId": 9381560,
						"useCollisionPoly": true,
						"duration": 1,
						"tag": ""
					},
					{
						"width": 64,
						"height": 64,
						"originX": 0.5,
						"originY": 0.5,
						"originalSource": "",
						"exportFormat": "lossless",
						"exportQuality": 0.8,
						"fileType": "image/png",
						"imageSpriteId": 6524699,
						"useCollisionPoly": true,
						"duration": 1,
						"tag": ""
					},
					{
						"width": 64,
						"height": 64,
						"originX": 0.5,
						"originY": 0.5,
						"originalSource": "",
						"exportFormat": "lossless",
						"exportQuality": 0.8,
						"fileType": "image/png",
						"imageSpriteId": 3363350,
						"useCollisionPoly": true,
						"duration": 1,
						"tag": ""
					},
					{
						"width": 64,
						"height": 64,
						"originX": 0.5,
						"originY": 0.5,
						"originalSource": "",
						"exportFormat": "lossless",
						"exportQuality": 0.8,
						"fileType": "image/png",
						"imageSpriteId": 4022964,
						"useCollisionPoly": true,
						"duration": 1,
						"tag": ""
					},
					{
						"width": 64,
						"height": 64,
						"originX": 0.5,
						"originY": 0.5,
						"originalSource": "",
						"exportFormat": "lossless",
						"exportQuality": 0.8,
						"fileType": "image/png",
						"imageSpriteId": 8441461,
						"useCollisionPoly": true,
						"duration": 1,
						"tag": ""
					},
					{
						"width": 64,
						"height": 64,
						"originX": 0.5,
						"originY": 0.5,
						"originalSource": "",
						"exportFormat": "lossless",
						"exportQuality": 0.8,
						"fileType": "image/png",
						"imageSpriteId": 8898917,
						"useCollisionPoly": true,
						"duration": 1,
						"tag": ""
					},
					{
						"width": 64,
						"height": 64,
						"originX": 0.5,
						"originY": 0.5,
						"originalSource": "",
						"exportFormat": "lossless",
						"exportQuality": 0.8,
						"fileType": "image/png",
						"imageSpriteId": 5830243,
						"useCollisionPoly": true,
						"duration": 1,
						"tag": ""
					},
					{
						"width": 64,
						"height": 64,
						"originX": 0.5,
						"originY": 0.5,
						"originalSource": "",
						"exportFormat": "lossless",
						"exportQuality": 0.8,
						"fileType": "image/png",
						"imageSpriteId": 8599574,
						"useCollisionPoly": true,
						"duration": 1,
						"tag": ""
					},
					{
						"width": 64,
						"height": 64,
						"originX": 0.5,
						"originY": 0.5,
						"originalSource": "",
						"exportFormat": "lossless",
						"exportQuality": 0.8,
						"fileType": "image/png",
						"imageSpriteId": 509257,
						"useCollisionPoly": true,
						"duration": 1,
						"tag": ""
					},
					{
						"width": 64,
						"height": 64,
						"originX": 0.5,
						"originY": 0.5,
						"originalSource": "",
						"exportFormat": "lossless",
						"exportQuality": 0.8,
						"fileType": "image/png",
						"imageSpriteId": 1279345,
						"useCollisionPoly": true,
						"duration": 1,
						"tag": ""
					},
					{
						"width": 64,
						"height": 64,
						"originX": 0.5,
						"originY": 0.5,
						"originalSource": "",
						"exportFormat": "lossless",
						"exportQuality": 0.8,
						"fileType": "image/png",
						"imageSpriteId": 9130976,
						"useCollisionPoly": true,
						"duration": 1,
						"tag": ""
					},
					{
						"width": 64,
						"height": 64,
						"originX": 0.5,
						"originY": 0.5,
						"originalSource": "",
						"exportFormat": "lossless",
						"exportQuality": 0.8,
						"fileType": "image/png",
						"imageSpriteId": 8054284,
						"useCollisionPoly": true,
						"duration": 1,
						"tag": ""
					},
					{
						"width": 64,
						"height": 64,
						"originX": 0.5,
						"originY": 0.5,
						"originalSource": "",
						"exportFormat": "lossless",
						"exportQuality": 0.8,
						"fileType": "image/png",
						"imageSpriteId": 7590199,
						"useCollisionPoly": true,
						"duration": 1,
						"tag": ""
					},
					{
						"width": 64,
						"height": 64,
						"originX": 0.5,
						"originY": 0.5,
						"originalSource": "",
						"exportFormat": "lossless",
						"exportQuality": 0.8,
						"fileType": "image/png",
						"imageSpriteId": 7904884,
						"useCollisionPoly": true,
						"duration": 1,
						"tag": ""
					},
					{
						"width": 64,
						"height": 64,
						"originX": 0.5,
						"originY": 0.5,
						"originalSource": "",
						"exportFormat": "lossless",
						"exportQuality": 0.8,
						"fileType": "image/png",
						"imageSpriteId": 6424993,
						"useCollisionPoly": true,
						"duration": 1,
						"tag": ""
					},
					{
						"width": 64,
						"height": 64,
						"originX": 0.5,
						"originY": 0.5,
						"originalSource": "",
						"exportFormat": "lossless",
						"exportQuality": 0.8,
						"fileType": "image/png",
						"imageSpriteId": 2394333,
						"useCollisionPoly": true,
						"duration": 1,
						"tag": ""
					},
					{
						"width": 64,
						"height": 64,
						"originX": 0.5,
						"originY": 0.5,
						"originalSource": "",
						"exportFormat": "lossless",
						"exportQuality": 0.8,
						"fileType": "image/png",
						"imageSpriteId": 3482265,
						"useCollisionPoly": true,
						"duration": 1,
						"tag": ""
					},
					{
						"width": 64,
						"height": 64,
						"originX": 0.5,
						"originY": 0.5,
						"originalSource": "",
						"exportFormat": "lossless",
						"exportQuality": 0.8,
						"fileType": "image/png",
						"imageSpriteId": 3193505,
						"useCollisionPoly": true,
						"duration": 1,
						"tag": ""
					},
					{
						"width": 64,
						"height": 64,
						"originX": 0.5,
						"originY": 0.5,
						"originalSource": "",
						"exportFormat": "lossless",
						"exportQuality": 0.8,
						"fileType": "image/png",
						"imageSpriteId": 918841,
						"useCollisionPoly": true,
						"duration": 1,
						"tag": ""
					},
					{
						"width": 64,
						"height": 64,
						"originX": 0.5,
						"originY": 0.5,
						"originalSource": "",
						"exportFormat": "lossless",
						"exportQuality": 0.8,
						"fileType": "image/png",
						"imageSpriteId": 2336581,
						"useCollisionPoly": true,
						"duration": 1,
						"tag": ""
					},
					{
						"width": 64,
						"height": 64,
						"originX": 0.5,
						"originY": 0.5,
						"originalSource": "",
						"exportFormat": "lossless",
						"exportQuality": 0.8,
						"fileType": "image/png",
						"imageSpriteId": 5924238,
						"useCollisionPoly": true,
						"duration": 1,
						"tag": ""
					},
					{
						"width": 64,
						"height": 64,
						"originX": 0.5,
						"originY": 0.5,
						"originalSource": "",
						"exportFormat": "lossless",
						"exportQuality": 0.8,
						"fileType": "image/png",
						"imageSpriteId": 5530388,
						"useCollisionPoly": true,
						"duration": 1,
						"tag": ""
					},
					{
						"width": 64,
						"height": 64,
						"originX": 0.5,
						"originY": 0.5,
						"originalSource": "",
						"exportFormat": "lossless",
						"exportQuality": 0.8,
						"fileType": "image/png",
						"imageSpriteId": 8887327,
						"useCollisionPoly": true,
						"duration": 1,
						"tag": ""
					},
					{
						"width": 64,
						"height": 64,
						"originX": 0.5,
						"originY": 0.5,
						"originalSource": "",
						"exportFormat": "lossless",
						"exportQuality": 0.8,
						"fileType": "image/png",
						"imageSpriteId": 1818554,
						"useCollisionPoly": true,
						"duration": 1,
						"tag": ""
					},
					{
						"width": 64,
						"height": 64,
						"originX": 0.5,
						"originY": 0.5,
						"originalSource": "",
						"exportFormat": "lossless",
						"exportQuality": 0.8,
						"fileType": "image/png",
						"imageSpriteId": 6117403,
						"useCollisionPoly": true,
						"duration": 1,
						"tag": ""
					},
					{
						"width": 64,
						"height": 64,
						"originX": 0.5,
						"originY": 0.5,
						"originalSource": "",
						"exportFormat": "lossless",
						"exportQuality": 0.8,
						"fileType": "image/png",
						"imageSpriteId": 1227810,
						"useCollisionPoly": true,
						"duration": 1,
						"tag": ""
					},
					{
						"width": 64,
						"height": 64,
						"originX": 0.5,
						"originY": 0.5,
						"originalSource": "",
						"exportFormat": "lossless",
						"exportQuality": 0.8,
						"fileType": "image/png",
						"imageSpriteId": 9360342,
						"useCollisionPoly": true,
						"duration": 1,
						"tag": ""
					},
					{
						"width": 64,
						"height": 64,
						"originX": 0.5,
						"originY": 0.5,
						"originalSource": "",
						"exportFormat": "lossless",
						"exportQuality": 0.8,
						"fileType": "image/png",
						"imageSpriteId": 6413113,
						"useCollisionPoly": true,
						"duration": 1,
						"tag": ""
					},
					{
						"width": 64,
						"height": 64,
						"originX": 0.5,
						"originY": 0.5,
						"originalSource": "",
						"exportFormat": "lossless",
						"exportQuality": 0.8,
						"fileType": "image/png",
						"imageSpriteId": 9021824,
						"useCollisionPoly": true,
						"duration": 1,
						"tag": ""
					},
					{
						"width": 64,
						"height": 64,
						"originX": 0.5,
						"originY": 0.5,
						"originalSource": "",
						"exportFormat": "lossless",
						"exportQuality": 0.8,
						"fileType": "image/png",
						"imageSpriteId": 1403619,
						"useCollisionPoly": true,
						"duration": 1,
						"tag": ""
					},
					{
						"width": 64,
						"height": 64,
						"originX": 0.5,
						"originY": 0.5,
						"originalSource": "",
						"exportFormat": "lossless",
						"exportQuality": 0.8,
						"fileType": "image/png",
						"imageSpriteId": 9006286,
						"useCollisionPoly": true,
						"duration": 1,
						"tag": ""
					},
					{
						"width": 64,
						"height": 64,
						"originX": 0.5,
						"originY": 0.5,
						"originalSource": "",
						"exportFormat": "lossless",
						"exportQuality": 0.8,
						"fileType": "image/png",
						"imageSpriteId": 9520833,
						"useCollisionPoly": true,
						"duration": 1,
						"tag": ""
					},
					{
						"width": 64,
						"height": 64,
						"originX": 0.5,
						"originY": 0.5,
						"originalSource": "",
						"exportFormat": "lossless",
						"exportQuality": 0.8,
						"fileType": "image/png",
						"imageSpriteId": 4824804,
						"useCollisionPoly": true,
						"duration": 1,
						"tag": ""
					},
					{
						"width": 64,
						"height": 64,
						"originX": 0.5,
						"originY": 0.5,
						"originalSource": "",
						"exportFormat": "lossless",
						"exportQuality": 0.8,
						"fileType": "image/png",
						"imageSpriteId": 3278197,
						"useCollisionPoly": true,
						"duration": 1,
						"tag": ""
					},
					{
						"width": 64,
						"height": 64,
						"originX": 0.5,
						"originY": 0.5,
						"originalSource": "",
						"exportFormat": "lossless",
						"exportQuality": 0.8,
						"fileType": "image/png",
						"imageSpriteId": 4288610,
						"useCollisionPoly": true,
						"duration": 1,
						"tag": ""
					},
					{
						"width": 64,
						"height": 64,
						"originX": 0.5,
						"originY": 0.5,
						"originalSource": "",
						"exportFormat": "lossless",
						"exportQuality": 0.8,
						"fileType": "image/png",
						"imageSpriteId": 3465172,
						"useCollisionPoly": true,
						"duration": 1,
						"tag": ""
					},
					{
						"width": 64,
						"height": 64,
						"originX": 0.5,
						"originY": 0.5,
						"originalSource": "",
						"exportFormat": "lossless",
						"exportQuality": 0.8,
						"fileType": "image/png",
						"imageSpriteId": 406426,
						"useCollisionPoly": true,
						"duration": 1,
						"tag": ""
					},
					{
						"width": 64,
						"height": 64,
						"originX": 0.5,
						"originY": 0.5,
						"originalSource": "",
						"exportFormat": "lossless",
						"exportQuality": 0.8,
						"fileType": "image/png",
						"imageSpriteId": 9880291,
						"useCollisionPoly": true,
						"duration": 1,
						"tag": ""
					},
					{
						"width": 64,
						"height": 64,
						"originX": 0.5,
						"originY": 0.5,
						"originalSource": "",
						"exportFormat": "lossless",
						"exportQuality": 0.8,
						"fileType": "image/png",
						"imageSpriteId": 8838968,
						"useCollisionPoly": true,
						"duration": 1,
						"tag": ""
					},
					{
						"width": 64,
						"height": 64,
						"originX": 0.5,
						"originY": 0.5,
						"originalSource": "",
						"exportFormat": "lossless",
						"exportQuality": 0.8,
						"fileType": "image/png",
						"imageSpriteId": 4338198,
						"useCollisionPoly": true,
						"duration": 1,
						"tag": ""
					},
					{
						"width": 64,
						"height": 64,
						"originX": 0.5,
						"originY": 0.5,
						"originalSource": "",
						"exportFormat": "lossless",
						"exportQuality": 0.8,
						"fileType": "image/png",
						"imageSpriteId": 4707852,
						"useCollisionPoly": true,
						"duration": 1,
						"tag": ""
					},
					{
						"width": 64,
						"height": 64,
						"originX": 0.5,
						"originY": 0.5,
						"originalSource": "",
						"exportFormat": "lossless",
						"exportQuality": 0.8,
						"fileType": "image/png",
						"imageSpriteId": 7037026,
						"useCollisionPoly": true,
						"duration": 1,
						"tag": ""
					},
					{
						"width": 64,
						"height": 64,
						"originX": 0.5,
						"originY": 0.5,
						"originalSource": "",
						"exportFormat": "lossless",
						"exportQuality": 0.8,
						"fileType": "image/png",
						"imageSpriteId": 3313039,
						"useCollisionPoly": true,
						"duration": 1,
						"tag": ""
					},
					{
						"width": 64,
						"height": 64,
						"originX": 0.5,
						"originY": 0.5,
						"originalSource": "",
						"exportFormat": "lossless",
						"exportQuality": 0.8,
						"fileType": "image/png",
						"imageSpriteId": 5574067,
						"useCollisionPoly": true,
						"duration": 1,
						"tag": ""
					},
					{
						"width": 64,
						"height": 64,
						"originX": 0.5,
						"originY": 0.5,
						"originalSource": "",
						"exportFormat": "lossless",
						"exportQuality": 0.8,
						"fileType": "image/png",
						"imageSpriteId": 5190574,
						"useCollisionPoly": true,
						"duration": 1,
						"tag": ""
					},
					{
						"width": 64,
						"height": 64,
						"originX": 0.5,
						"originY": 0.5,
						"originalSource": "",
						"exportFormat": "lossless",
						"exportQuality": 0.8,
						"fileType": "image/png",
						"imageSpriteId": 8201437,
						"useCollisionPoly": true,
						"duration": 1,
						"tag": ""
					},
					{
						"width": 64,
						"height": 64,
						"originX": 0.5,
						"originY": 0.5,
						"originalSource": "",
						"exportFormat": "lossless",
						"exportQuality": 0.8,
						"fileType": "image/png",
						"imageSpriteId": 5885647,
						"useCollisionPoly": true,
						"duration": 1,
						"tag": ""
					},
					{
						"width": 64,
						"height": 64,
						"originX": 0.5,
						"originY": 0.5,
						"originalSource": "",
						"exportFormat": "lossless",
						"exportQuality": 0.8,
						"fileType": "image/png",
						"imageSpriteId": 701131,
						"useCollisionPoly": true,
						"duration": 1,
						"tag": ""
					},
					{
						"width": 64,
						"height": 64,
						"originX": 0.5,
						"originY": 0.5,
						"originalSource": "",
						"exportFormat": "lossless",
						"exportQuality": 0.8,
						"fileType": "image/png",
						"imageSpriteId": 755908,
						"useCollisionPoly": true,
						"duration": 1,
						"tag": ""
					},
					{
						"width": 64,
						"height": 64,
						"originX": 0.5,
						"originY": 0.5,
						"originalSource": "",
						"exportFormat": "lossless",
						"exportQuality": 0.8,
						"fileType": "image/png",
						"imageSpriteId": 5492672,
						"useCollisionPoly": true,
						"duration": 1,
						"tag": ""
					},
					{
						"width": 64,
						"height": 64,
						"originX": 0.5,
						"originY": 0.5,
						"originalSource": "",
						"exportFormat": "lossless",
						"exportQuality": 0.8,
						"fileType": "image/png",
						"imageSpriteId": 6795416,
						"useCollisionPoly": true,
						"duration": 1,
						"tag": ""
					},
					{
						"width": 64,
						"height": 64,
						"originX": 0.5,
						"originY": 0.5,
						"originalSource": "",
						"exportFormat": "lossless",
						"exportQuality": 0.8,
						"fileType": "image/png",
						"imageSpriteId": 4774407,
						"useCollisionPoly": true,
						"duration": 1,
						"tag": ""
					},
					{
						"width": 64,
						"height": 64,
						"originX": 0.5,
						"originY": 0.5,
						"originalSource": "",
						"exportFormat": "lossless",
						"exportQuality": 0.8,
						"fileType": "image/png",
						"imageSpriteId": 5772300,
						"useCollisionPoly": true,
						"duration": 1,
						"tag": ""
					},
					{
						"width": 64,
						"height": 64,
						"originX": 0.5,
						"originY": 0.5,
						"originalSource": "",
						"exportFormat": "lossless",
						"exportQuality": 0.8,
						"fileType": "image/png",
						"imageSpriteId": 1668365,
						"useCollisionPoly": true,
						"duration": 1,
						"tag": ""
					},
					{
						"width": 64,
						"height": 64,
						"originX": 0.5,
						"originY": 0.5,
						"originalSource": "",
						"exportFormat": "lossless",
						"exportQuality": 0.8,
						"fileType": "image/png",
						"imageSpriteId": 5482655,
						"useCollisionPoly": true,
						"duration": 1,
						"tag": ""
					},
					{
						"width": 64,
						"height": 64,
						"originX": 0.5,
						"originY": 0.5,
						"originalSource": "",
						"exportFormat": "lossless",
						"exportQuality": 0.8,
						"fileType": "image/png",
						"imageSpriteId": 517436,
						"useCollisionPoly": true,
						"duration": 1,
						"tag": ""
					},
					{
						"width": 64,
						"height": 64,
						"originX": 0.5,
						"originY": 0.5,
						"originalSource": "",
						"exportFormat": "lossless",
						"exportQuality": 0.8,
						"fileType": "image/png",
						"imageSpriteId": 9221685,
						"useCollisionPoly": true,
						"duration": 1,
						"tag": ""
					},
					{
						"width": 64,
						"height": 64,
						"originX": 0.5,
						"originY": 0.5,
						"originalSource": "",
						"exportFormat": "lossless",
						"exportQuality": 0.8,
						"fileType": "image/png",
						"imageSpriteId": 3161141,
						"useCollisionPoly": true,
						"duration": 1,
						"tag": ""
					},
					{
						"width": 64,
						"height": 64,
						"originX": 0.5,
						"originY": 0.5,
						"originalSource": "",
						"exportFormat": "lossless",
						"exportQuality": 0.8,
						"fileType": "image/png",
						"imageSpriteId": 6602973,
						"useCollisionPoly": true,
						"duration": 1,
						"tag": ""
					},
					{
						"width": 64,
						"height": 64,
						"originX": 0.5,
						"originY": 0.5,
						"originalSource": "",
						"exportFormat": "lossless",
						"exportQuality": 0.8,
						"fileType": "image/png",
						"imageSpriteId": 89420,
						"useCollisionPoly": true,
						"duration": 1,
						"tag": ""
					},
					{
						"width": 64,
						"height": 64,
						"originX": 0.5,
						"originY": 0.5,
						"originalSource": "",
						"exportFormat": "lossless",
						"exportQuality": 0.8,
						"fileType": "image/png",
						"imageSpriteId": 8411904,
						"useCollisionPoly": true,
						"duration": 1,
						"tag": ""
					},
					{
						"width": 64,
						"height": 64,
						"originX": 0.5,
						"originY": 0.5,
						"originalSource": "",
						"exportFormat": "lossless",
						"exportQuality": 0.8,
						"fileType": "image/png",
						"imageSpriteId": 4194720,
						"useCollisionPoly": true,
						"duration": 1,
						"tag": ""
					},
					{
						"width": 64,
						"height": 64,
						"originX": 0.5,
						"originY": 0.5,
						"originalSource": "",
						"exportFormat": "lossless",
						"exportQuality": 0.8,
						"fileType": "image/png",
						"imageSpriteId": 4407896,
						"useCollisionPoly": true,
						"duration": 1,
						"tag": ""
					},
					{
						"width": 64,
						"height": 64,
						"originX": 0.5,
						"originY": 0.5,
						"originalSource": "",
						"exportFormat": "lossless",
						"exportQuality": 0.8,
						"fileType": "image/png",
						"imageSpriteId": 7850706,
						"useCollisionPoly": true,
						"duration": 1,
						"tag": ""
					},
					{
						"width": 64,
						"height": 64,
						"originX": 0.5,
						"originY": 0.5,
						"originalSource": "",
						"exportFormat": "lossless",
						"exportQuality": 0.8,
						"fileType": "image/png",
						"imageSpriteId": 5962394,
						"useCollisionPoly": true,
						"duration": 1,
						"tag": ""
					},
					{
						"width": 64,
						"height": 64,
						"originX": 0.5,
						"originY": 0.5,
						"originalSource": "",
						"exportFormat": "lossless",
						"exportQuality": 0.8,
						"fileType": "image/png",
						"imageSpriteId": 6720429,
						"useCollisionPoly": true,
						"duration": 1,
						"tag": ""
					},
					{
						"width": 64,
						"height": 64,
						"originX": 0.5,
						"originY": 0.5,
						"originalSource": "",
						"exportFormat": "lossless",
						"exportQuality": 0.8,
						"fileType": "image/png",
						"imageSpriteId": 2590939,
						"useCollisionPoly": true,
						"duration": 1,
						"tag": ""
					},
					{
						"width": 64,
						"height": 64,
						"originX": 0.5,
						"originY": 0.5,
						"originalSource": "",
						"exportFormat": "lossless",
						"exportQuality": 0.8,
						"fileType": "image/png",
						"imageSpriteId": 164590,
						"useCollisionPoly": true,
						"duration": 1,
						"tag": ""
					},
					{
						"width": 64,
						"height": 64,
						"originX": 0.5,
						"originY": 0.5,
						"originalSource": "",
						"exportFormat": "lossless",
						"exportQuality": 0.8,
						"fileType": "image/png",
						"imageSpriteId": 7844058,
						"useCollisionPoly": true,
						"duration": 1,
						"tag": ""
					},
					{
						"width": 64,
						"height": 64,
						"originX": 0.5,
						"originY": 0.5,
						"originalSource": "",
						"exportFormat": "lossless",
						"exportQuality": 0.8,
						"fileType": "image/png",
						"imageSpriteId": 1604463,
						"useCollisionPoly": true,
						"duration": 1,
						"tag": ""
					},
					{
						"width": 64,
						"height": 64,
						"originX": 0.5,
						"originY": 0.5,
						"originalSource": "",
						"exportFormat": "lossless",
						"exportQuality": 0.8,
						"fileType": "image/png",
						"imageSpriteId": 7868860,
						"useCollisionPoly": true,
						"duration": 1,
						"tag": ""
					},
					{
						"width": 64,
						"height": 64,
						"originX": 0.5,
						"originY": 0.5,
						"originalSource": "",
						"exportFormat": "lossless",
						"exportQuality": 0.8,
						"fileType": "image/png",
						"imageSpriteId": 3413756,
						"useCollisionPoly": true,
						"duration": 1,
						"tag": ""
					},
					{
						"width": 64,
						"height": 64,
						"originX": 0.5,
						"originY": 0.5,
						"originalSource": "",
						"exportFormat": "lossless",
						"exportQuality": 0.8,
						"fileType": "image/png",
						"imageSpriteId": 4764022,
						"useCollisionPoly": true,
						"duration": 1,
						"tag": ""
					},
					{
						"width": 64,
						"height": 64,
						"originX": 0.5,
						"originY": 0.5,
						"originalSource": "",
						"exportFormat": "lossless",
						"exportQuality": 0.8,
						"fileType": "image/png",
						"imageSpriteId": 1946461,
						"useCollisionPoly": true,
						"duration": 1,
						"tag": ""
					},
					{
						"width": 64,
						"height": 64,
						"originX": 0.5,
						"originY": 0.5,
						"originalSource": "",
						"exportFormat": "lossless",
						"exportQuality": 0.8,
						"fileType": "image/png",
						"imageSpriteId": 2590946,
						"useCollisionPoly": true,
						"duration": 1,
						"tag": ""
					},
					{
						"width": 64,
						"height": 64,
						"originX": 0.5,
						"originY": 0.5,
						"originalSource": "",
						"exportFormat": "lossless",
						"exportQuality": 0.8,
						"fileType": "image/png",
						"imageSpriteId": 3033668,
						"useCollisionPoly": true,
						"duration": 1,
						"tag": ""
					},
					{
						"width": 64,
						"height": 64,
						"originX": 0.5,
						"originY": 0.5,
						"originalSource": "",
						"exportFormat": "lossless",
						"exportQuality": 0.8,
						"fileType": "image/png",
						"imageSpriteId": 7311675,
						"useCollisionPoly": true,
						"duration": 1,
						"tag": ""
					},
					{
						"width": 64,
						"height": 64,
						"originX": 0.5,
						"originY": 0.5,
						"originalSource": "",
						"exportFormat": "lossless",
						"exportQuality": 0.8,
						"fileType": "image/png",
						"imageSpriteId": 3017286,
						"useCollisionPoly": true,
						"duration": 1,
						"tag": ""
					},
					{
						"width": 64,
						"height": 64,
						"originX": 0.5,
						"originY": 0.5,
						"originalSource": "",
						"exportFormat": "lossless",
						"exportQuality": 0.8,
						"fileType": "image/png",
						"imageSpriteId": 926119,
						"useCollisionPoly": true,
						"duration": 1,
						"tag": ""
					},
					{
						"width": 64,
						"height": 64,
						"originX": 0.5,
						"originY": 0.5,
						"originalSource": "",
						"exportFormat": "lossless",
						"exportQuality": 0.8,
						"fileType": "image/png",
						"imageSpriteId": 4755573,
						"useCollisionPoly": true,
						"duration": 1,
						"tag": ""
					},
					{
						"width": 64,
						"height": 64,
						"originX": 0.5,
						"originY": 0.5,
						"originalSource": "",
						"exportFormat": "lossless",
						"exportQuality": 0.8,
						"fileType": "image/png",
						"imageSpriteId": 3463991,
						"useCollisionPoly": true,
						"duration": 1,
						"tag": ""
					},
					{
						"width": 64,
						"height": 64,
						"originX": 0.5,
						"originY": 0.5,
						"originalSource": "",
						"exportFormat": "lossless",
						"exportQuality": 0.8,
						"fileType": "image/png",
						"imageSpriteId": 9983073,
						"useCollisionPoly": true,
						"duration": 1,
						"tag": ""
					},
					{
						"width": 64,
						"height": 64,
						"originX": 0.5,
						"originY": 0.5,
						"originalSource": "",
						"exportFormat": "lossless",
						"exportQuality": 0.8,
						"fileType": "image/png",
						"imageSpriteId": 1627967,
						"useCollisionPoly": true,
						"duration": 1,
						"tag": ""
					},
					{
						"width": 64,
						"height": 64,
						"originX": 0.5,
						"originY": 0.5,
						"originalSource": "",
						"exportFormat": "lossless",
						"exportQuality": 0.8,
						"fileType": "image/png",
						"imageSpriteId": 5825839,
						"useCollisionPoly": true,
						"duration": 1,
						"tag": ""
					},
					{
						"width": 64,
						"height": 64,
						"originX": 0.5,
						"originY": 0.5,
						"originalSource": "",
						"exportFormat": "lossless",
						"exportQuality": 0.8,
						"fileType": "image/png",
						"imageSpriteId": 3809156,
						"useCollisionPoly": true,
						"duration": 1,
						"tag": ""
					},
					{
						"width": 64,
						"height": 64,
						"originX": 0.5,
						"originY": 0.5,
						"originalSource": "",
						"exportFormat": "lossless",
						"exportQuality": 0.8,
						"fileType": "image/png",
						"imageSpriteId": 7146590,
						"useCollisionPoly": true,
						"duration": 1,
						"tag": ""
					},
					{
						"width": 64,
						"height": 64,
						"originX": 0.5,
						"originY": 0.5,
						"originalSource": "",
						"exportFormat": "lossless",
						"exportQuality": 0.8,
						"fileType": "image/png",
						"imageSpriteId": 702006,
						"useCollisionPoly": true,
						"duration": 1,
						"tag": ""
					},
					{
						"width": 64,
						"height": 64,
						"originX": 0.5,
						"originY": 0.5,
						"originalSource": "",
						"exportFormat": "lossless",
						"exportQuality": 0.8,
						"fileType": "image/png",
						"imageSpriteId": 994538,
						"useCollisionPoly": true,
						"duration": 1,
						"tag": ""
					},
					{
						"width": 64,
						"height": 64,
						"originX": 0.5,
						"originY": 0.5,
						"originalSource": "",
						"exportFormat": "lossless",
						"exportQuality": 0.8,
						"fileType": "image/png",
						"imageSpriteId": 4506635,
						"useCollisionPoly": true,
						"duration": 1,
						"tag": ""
					},
					{
						"width": 64,
						"height": 64,
						"originX": 0.5,
						"originY": 0.5,
						"originalSource": "",
						"exportFormat": "lossless",
						"exportQuality": 0.8,
						"fileType": "image/png",
						"imageSpriteId": 6690105,
						"useCollisionPoly": true,
						"duration": 1,
						"tag": ""
					},
					{
						"width": 64,
						"height": 64,
						"originX": 0.5,
						"originY": 0.5,
						"originalSource": "",
						"exportFormat": "lossless",
						"exportQuality": 0.8,
						"fileType": "image/png",
						"imageSpriteId": 9300844,
						"useCollisionPoly": true,
						"duration": 1,
						"tag": ""
					},
					{
						"width": 64,
						"height": 64,
						"originX": 0.5,
						"originY": 0.5,
						"originalSource": "",
						"exportFormat": "lossless",
						"exportQuality": 0.8,
						"fileType": "image/png",
						"imageSpriteId": 7534041,
						"useCollisionPoly": true,
						"duration": 1,
						"tag": ""
					},
					{
						"width": 64,
						"height": 64,
						"originX": 0.5,
						"originY": 0.5,
						"originalSource": "",
						"exportFormat": "lossless",
						"exportQuality": 0.8,
						"fileType": "image/png",
						"imageSpriteId": 3777973,
						"useCollisionPoly": true,
						"duration": 1,
						"tag": ""
					},
					{
						"width": 64,
						"height": 64,
						"originX": 0.5,
						"originY": 0.5,
						"originalSource": "",
						"exportFormat": "lossless",
						"exportQuality": 0.8,
						"fileType": "image/png",
						"imageSpriteId": 1498354,
						"useCollisionPoly": true,
						"duration": 1,
						"tag": ""
					},
					{
						"width": 64,
						"height": 64,
						"originX": 0.5,
						"originY": 0.5,
						"originalSource": "",
						"exportFormat": "lossless",
						"exportQuality": 0.8,
						"fileType": "image/png",
						"imageSpriteId": 4187917,
						"useCollisionPoly": true,
						"duration": 1,
						"tag": ""
					},
					{
						"width": 64,
						"height": 64,
						"originX": 0.5,
						"originY": 0.5,
						"originalSource": "",
						"exportFormat": "lossless",
						"exportQuality": 0.8,
						"fileType": "image/png",
						"imageSpriteId": 2233675,
						"useCollisionPoly": true,
						"duration": 1,
						"tag": ""
					},
					{
						"width": 64,
						"height": 64,
						"originX": 0.5,
						"originY": 0.5,
						"originalSource": "",
						"exportFormat": "lossless",
						"exportQuality": 0.8,
						"fileType": "image/png",
						"imageSpriteId": 5696889,
						"useCollisionPoly": true,
						"duration": 1,
						"tag": ""
					},
					{
						"width": 64,
						"height": 64,
						"originX": 0.5,
						"originY": 0.5,
						"originalSource": "",
						"exportFormat": "lossless",
						"exportQuality": 0.8,
						"fileType": "image/png",
						"imageSpriteId": 8350381,
						"useCollisionPoly": true,
						"duration": 1,
						"tag": ""
					},
					{
						"width": 64,
						"height": 64,
						"originX": 0.5,
						"originY": 0.5,
						"originalSource": "",
						"exportFormat": "lossless",
						"exportQuality": 0.8,
						"fileType": "image/png",
						"imageSpriteId": 6962820,
						"useCollisionPoly": true,
						"duration": 1,
						"tag": ""
					},
					{
						"width": 64,
						"height": 64,
						"originX": 0.5,
						"originY": 0.5,
						"originalSource": "",
						"exportFormat": "lossless",
						"exportQuality": 0.8,
						"fileType": "image/png",
						"imageSpriteId": 9678351,
						"useCollisionPoly": true,
						"duration": 1,
						"tag": ""
					},
					{
						"width": 64,
						"height": 64,
						"originX": 0.5,
						"originY": 0.5,
						"originalSource": "",
						"exportFormat": "lossless",
						"exportQuality": 0.8,
						"fileType": "image/png",
						"imageSpriteId": 5326626,
						"useCollisionPoly": true,
						"duration": 1,
						"tag": ""
					},
					{
						"width": 64,
						"height": 64,
						"originX": 0.5,
						"originY": 0.5,
						"originalSource": "",
						"exportFormat": "lossless",
						"exportQuality": 0.8,
						"fileType": "image/png",
						"imageSpriteId": 6492876,
						"useCollisionPoly": true,
						"duration": 1,
						"tag": ""
					},
					{
						"width": 64,
						"height": 64,
						"originX": 0.5,
						"originY": 0.5,
						"originalSource": "",
						"exportFormat": "lossless",
						"exportQuality": 0.8,
						"fileType": "image/png",
						"imageSpriteId": 4496005,
						"useCollisionPoly": true,
						"duration": 1,
						"tag": ""
					},
					{
						"width": 64,
						"height": 64,
						"originX": 0.5,
						"originY": 0.5,
						"originalSource": "",
						"exportFormat": "lossless",
						"exportQuality": 0.8,
						"fileType": "image/png",
						"imageSpriteId": 9199238,
						"useCollisionPoly": true,
						"duration": 1,
						"tag": ""
					},
					{
						"width": 64,
						"height": 64,
						"originX": 0.5,
						"originY": 0.5,
						"originalSource": "",
						"exportFormat": "lossless",
						"exportQuality": 0.8,
						"fileType": "image/png",
						"imageSpriteId": 9161619,
						"useCollisionPoly": true,
						"duration": 1,
						"tag": ""
					},
					{
						"width": 64,
						"height": 64,
						"originX": 0.5,
						"originY": 0.5,
						"originalSource": "",
						"exportFormat": "lossless",
						"exportQuality": 0.8,
						"fileType": "image/png",
						"imageSpriteId": 2236988,
						"useCollisionPoly": true,
						"duration": 1,
						"tag": ""
					},
					{
						"width": 64,
						"height": 64,
						"originX": 0.5,
						"originY": 0.5,
						"originalSource": "",
						"exportFormat": "lossless",
						"exportQuality": 0.8,
						"fileType": "image/png",
						"imageSpriteId": 1983071,
						"useCollisionPoly": true,
						"duration": 1,
						"tag": ""
					},
					{
						"width": 64,
						"height": 64,
						"originX": 0.5,
						"originY": 0.5,
						"originalSource": "",
						"exportFormat": "lossless",
						"exportQuality": 0.8,
						"fileType": "image/png",
						"imageSpriteId": 5594564,
						"useCollisionPoly": true,
						"duration": 1,
						"tag": ""
					},
					{
						"width": 64,
						"height": 64,
						"originX": 0.5,
						"originY": 0.5,
						"originalSource": "",
						"exportFormat": "lossless",
						"exportQuality": 0.8,
						"fileType": "image/png",
						"imageSpriteId": 2750580,
						"useCollisionPoly": true,
						"duration": 1,
						"tag": ""
					},
					{
						"width": 64,
						"height": 64,
						"originX": 0.5,
						"originY": 0.5,
						"originalSource": "",
						"exportFormat": "lossless",
						"exportQuality": 0.8,
						"fileType": "image/png",
						"imageSpriteId": 1141312,
						"useCollisionPoly": true,
						"duration": 1,
						"tag": ""
					},
					{
						"width": 64,
						"height": 64,
						"originX": 0.5,
						"originY": 0.5,
						"originalSource": "",
						"exportFormat": "lossless",
						"exportQuality": 0.8,
						"fileType": "image/png",
						"imageSpriteId": 9213446,
						"useCollisionPoly": true,
						"duration": 1,
						"tag": ""
					},
					{
						"width": 64,
						"height": 64,
						"originX": 0.5,
						"originY": 0.5,
						"originalSource": "",
						"exportFormat": "lossless",
						"exportQuality": 0.8,
						"fileType": "image/png",
						"imageSpriteId": 8777411,
						"useCollisionPoly": true,
						"duration": 1,
						"tag": ""
					},
					{
						"width": 64,
						"height": 64,
						"originX": 0.5,
						"originY": 0.5,
						"originalSource": "",
						"exportFormat": "lossless",
						"exportQuality": 0.8,
						"fileType": "image/png",
						"imageSpriteId": 8756595,
						"useCollisionPoly": true,
						"duration": 1,
						"tag": ""
					},
					{
						"width": 64,
						"height": 64,
						"originX": 0.5,
						"originY": 0.5,
						"originalSource": "",
						"exportFormat": "lossless",
						"exportQuality": 0.8,
						"fileType": "image/png",
						"imageSpriteId": 4042102,
						"useCollisionPoly": true,
						"duration": 1,
						"tag": ""
					},
					{
						"width": 64,
						"height": 64,
						"originX": 0.5,
						"originY": 0.5,
						"originalSource": "",
						"exportFormat": "lossless",
						"exportQuality": 0.8,
						"fileType": "image/png",
						"imageSpriteId": 8486595,
						"useCollisionPoly": true,
						"duration": 1,
						"tag": ""
					},
					{
						"width": 64,
						"height": 64,
						"originX": 0.5,
						"originY": 0.5,
						"originalSource": "",
						"exportFormat": "lossless",
						"exportQuality": 0.8,
						"fileType": "image/png",
						"imageSpriteId": 1787753,
						"useCollisionPoly": true,
						"duration": 1,
						"tag": ""
					},
					{
						"width": 64,
						"height": 64,
						"originX": 0.5,
						"originY": 0.5,
						"originalSource": "",
						"exportFormat": "lossless",
						"exportQuality": 0.8,
						"fileType": "image/png",
						"imageSpriteId": 589409,
						"useCollisionPoly": true,
						"duration": 1,
						"tag": ""
					},
					{
						"width": 64,
						"height": 64,
						"originX": 0.5,
						"originY": 0.5,
						"originalSource": "",
						"exportFormat": "lossless",
						"exportQuality": 0.8,
						"fileType": "image/png",
						"imageSpriteId": 370350,
						"useCollisionPoly": true,
						"duration": 1,
						"tag": ""
					},
					{
						"width": 64,
						"height": 64,
						"originX": 0.5,
						"originY": 0.5,
						"originalSource": "",
						"exportFormat": "lossless",
						"exportQuality": 0.8,
						"fileType": "image/png",
						"imageSpriteId": 4458434,
						"useCollisionPoly": true,
						"duration": 1,
						"tag": ""
					},
					{
						"width": 64,
						"height": 64,
						"originX": 0.5,
						"originY": 0.5,
						"originalSource": "",
						"exportFormat": "lossless",
						"exportQuality": 0.8,
						"fileType": "image/png",
						"imageSpriteId": 1493200,
						"useCollisionPoly": true,
						"duration": 1,
						"tag": ""
					},
					{
						"width": 64,
						"height": 64,
						"originX": 0.5,
						"originY": 0.5,
						"originalSource": "",
						"exportFormat": "lossless",
						"exportQuality": 0.8,
						"fileType": "image/png",
						"imageSpriteId": 1050976,
						"useCollisionPoly": true,
						"duration": 1,
						"tag": ""
					},
					{
						"width": 64,
						"height": 64,
						"originX": 0.5,
						"originY": 0.5,
						"originalSource": "",
						"exportFormat": "lossless",
						"exportQuality": 0.8,
						"fileType": "image/png",
						"imageSpriteId": 613452,
						"useCollisionPoly": true,
						"duration": 1,
						"tag": ""
					},
					{
						"width": 64,
						"height": 64,
						"originX": 0.5,
						"originY": 0.5,
						"originalSource": "",
						"exportFormat": "lossless",
						"exportQuality": 0.8,
						"fileType": "image/png",
						"imageSpriteId": 9599919,
						"useCollisionPoly": true,
						"duration": 1,
						"tag": ""
					},
					{
						"width": 64,
						"height": 64,
						"originX": 0.5,
						"originY": 0.5,
						"originalSource": "",
						"exportFormat": "lossless",
						"exportQuality": 0.8,
						"fileType": "image/png",
						"imageSpriteId": 6640587,
						"useCollisionPoly": true,
						"duration": 1,
						"tag": ""
					},
					{
						"width": 64,
						"height": 64,
						"originX": 0.5,
						"originY": 0.5,
						"originalSource": "",
						"exportFormat": "lossless",
						"exportQuality": 0.8,
						"fileType": "image/png",
						"imageSpriteId": 4088495,
						"useCollisionPoly": true,
						"duration": 1,
						"tag": ""
					},
					{
						"width": 64,
						"height": 64,
						"originX": 0.5,
						"originY": 0.5,
						"originalSource": "",
						"exportFormat": "lossless",
						"exportQuality": 0.8,
						"fileType": "image/png",
						"imageSpriteId": 9094453,
						"useCollisionPoly": true,
						"duration": 1,
						"tag": ""
					},
					{
						"width": 64,
						"height": 64,
						"originX": 0.5,
						"originY": 0.5,
						"originalSource": "",
						"exportFormat": "lossless",
						"exportQuality": 0.8,
						"fileType": "image/png",
						"imageSpriteId": 7001882,
						"useCollisionPoly": true,
						"duration": 1,
						"tag": ""
					},
					{
						"width": 64,
						"height": 64,
						"originX": 0.5,
						"originY": 0.5,
						"originalSource": "",
						"exportFormat": "lossless",
						"exportQuality": 0.8,
						"fileType": "image/png",
						"imageSpriteId": 1317788,
						"useCollisionPoly": true,
						"duration": 1,
						"tag": ""
					},
					{
						"width": 64,
						"height": 64,
						"originX": 0.5,
						"originY": 0.5,
						"originalSource": "",
						"exportFormat": "lossless",
						"exportQuality": 0.8,
						"fileType": "image/png",
						"imageSpriteId": 2634788,
						"useCollisionPoly": true,
						"duration": 1,
						"tag": ""
					},
					{
						"width": 64,
						"height": 64,
						"originX": 0.5,
						"originY": 0.5,
						"originalSource": "",
						"exportFormat": "lossless",
						"exportQuality": 0.8,
						"fileType": "image/png",
						"imageSpriteId": 4501695,
						"useCollisionPoly": true,
						"duration": 1,
						"tag": ""
					},
					{
						"width": 64,
						"height": 64,
						"originX": 0.5,
						"originY": 0.5,
						"originalSource": "",
						"exportFormat": "lossless",
						"exportQuality": 0.8,
						"fileType": "image/png",
						"imageSpriteId": 7953387,
						"useCollisionPoly": true,
						"duration": 1,
						"tag": ""
					},
					{
						"width": 64,
						"height": 64,
						"originX": 0.5,
						"originY": 0.5,
						"originalSource": "",
						"exportFormat": "lossless",
						"exportQuality": 0.8,
						"fileType": "image/png",
						"imageSpriteId": 9495574,
						"useCollisionPoly": true,
						"duration": 1,
						"tag": ""
					},
					{
						"width": 64,
						"height": 64,
						"originX": 0.5,
						"originY": 0.5,
						"originalSource": "",
						"exportFormat": "lossless",
						"exportQuality": 0.8,
						"fileType": "image/png",
						"imageSpriteId": 6735819,
						"useCollisionPoly": true,
						"duration": 1,
						"tag": ""
					},
					{
						"width": 64,
						"height": 64,
						"originX": 0.5,
						"originY": 0.5,
						"originalSource": "",
						"exportFormat": "lossless",
						"exportQuality": 0.8,
						"fileType": "image/png",
						"imageSpriteId": 6167146,
						"useCollisionPoly": true,
						"duration": 1,
						"tag": ""
					},
					{
						"width": 64,
						"height": 64,
						"originX": 0.5,
						"originY": 0.5,
						"originalSource": "",
						"exportFormat": "lossless",
						"exportQuality": 0.8,
						"fileType": "image/png",
						"imageSpriteId": 6364504,
						"useCollisionPoly": true,
						"duration": 1,
						"tag": ""
					},
					{
						"width": 64,
						"height": 64,
						"originX": 0.5,
						"originY": 0.5,
						"originalSource": "",
						"exportFormat": "lossless",
						"exportQuality": 0.8,
						"fileType": "image/png",
						"imageSpriteId": 6067465,
						"useCollisionPoly": true,
						"duration": 1,
						"tag": ""
					},
					{
						"width": 64,
						"height": 64,
						"originX": 0.5,
						"originY": 0.5,
						"originalSource": "",
						"exportFormat": "lossless",
						"exportQuality": 0.8,
						"fileType": "image/png",
						"imageSpriteId": 420764,
						"useCollisionPoly": true,
						"duration": 1,
						"tag": ""
					},
					{
						"width": 64,
						"height": 64,
						"originX": 0.5,
						"originY": 0.5,
						"originalSource": "",
						"exportFormat": "lossless",
						"exportQuality": 0.8,
						"fileType": "image/png",
						"imageSpriteId": 8237934,
						"useCollisionPoly": true,
						"duration": 1,
						"tag": ""
					},
					{
						"width": 64,
						"height": 64,
						"originX": 0.5,
						"originY": 0.5,
						"originalSource": "",
						"exportFormat": "lossless",
						"exportQuality": 0.8,
						"fileType": "image/png",
						"imageSpriteId": 9303217,
						"useCollisionPoly": true,
						"duration": 1,
						"tag": ""
					},
					{
						"width": 64,
						"height": 64,
						"originX": 0.5,
						"originY": 0.5,
						"originalSource": "",
						"exportFormat": "lossless",
						"exportQuality": 0.8,
						"fileType": "image/png",
						"imageSpriteId": 8197725,
						"useCollisionPoly": true,
						"duration": 1,
						"tag": ""
					},
					{
						"width": 64,
						"height": 64,
						"originX": 0.5,
						"originY": 0.5,
						"originalSource": "",
						"exportFormat": "lossless",
						"exportQuality": 0.8,
						"fileType": "image/png",
						"imageSpriteId": 2359814,
						"useCollisionPoly": true,
						"duration": 1,
						"tag": ""
					},
					{
						"width": 64,
						"height": 64,
						"originX": 0.5,
						"originY": 0.5,
						"originalSource": "",
						"exportFormat": "lossless",
						"exportQuality": 0.8,
						"fileType": "image/png",
						"imageSpriteId": 1923346,
						"useCollisionPoly": true,
						"duration": 1,
						"tag": ""
					},
					{
						"width": 64,
						"height": 64,
						"originX": 0.5,
						"originY": 0.5,
						"originalSource": "",
						"exportFormat": "lossless",
						"exportQuality": 0.8,
						"fileType": "image/png",
						"imageSpriteId": 9074684,
						"useCollisionPoly": true,
						"duration": 1,
						"tag": ""
					},
					{
						"width": 64,
						"height": 64,
						"originX": 0.5,
						"originY": 0.5,
						"originalSource": "",
						"exportFormat": "lossless",
						"exportQuality": 0.8,
						"fileType": "image/png",
						"imageSpriteId": 8344115,
						"useCollisionPoly": true,
						"duration": 1,
						"tag": ""
					},
					{
						"width": 64,
						"height": 64,
						"originX": 0.5,
						"originY": 0.5,
						"originalSource": "",
						"exportFormat": "lossless",
						"exportQuality": 0.8,
						"fileType": "image/png",
						"imageSpriteId": 2759040,
						"useCollisionPoly": true,
						"duration": 1,
						"tag": ""
					},
					{
						"width": 64,
						"height": 64,
						"originX": 0.5,
						"originY": 0.5,
						"originalSource": "",
						"exportFormat": "lossless",
						"exportQuality": 0.8,
						"fileType": "image/png",
						"imageSpriteId": 8670054,
						"useCollisionPoly": true,
						"duration": 1,
						"tag": ""
					},
					{
						"width": 64,
						"height": 64,
						"originX": 0.5,
						"originY": 0.5,
						"originalSource": "",
						"exportFormat": "lossless",
						"exportQuality": 0.8,
						"fileType": "image/png",
						"imageSpriteId": 8074941,
						"useCollisionPoly": true,
						"duration": 1,
						"tag": ""
					},
					{
						"width": 64,
						"height": 64,
						"originX": 0.5,
						"originY": 0.5,
						"originalSource": "",
						"exportFormat": "lossless",
						"exportQuality": 0.8,
						"fileType": "image/png",
						"imageSpriteId": 8075767,
						"useCollisionPoly": true,
						"duration": 1,
						"tag": ""
					},
					{
						"width": 64,
						"height": 64,
						"originX": 0.5,
						"originY": 0.5,
						"originalSource": "",
						"exportFormat": "lossless",
						"exportQuality": 0.8,
						"fileType": "image/png",
						"imageSpriteId": 1748601,
						"useCollisionPoly": true,
						"duration": 1,
						"tag": ""
					},
					{
						"width": 64,
						"height": 64,
						"originX": 0.5,
						"originY": 0.5,
						"originalSource": "",
						"exportFormat": "lossless",
						"exportQuality": 0.8,
						"fileType": "image/png",
						"imageSpriteId": 839095,
						"useCollisionPoly": true,
						"duration": 1,
						"tag": ""
					},
					{
						"width": 64,
						"height": 64,
						"originX": 0.5,
						"originY": 0.5,
						"originalSource": "",
						"exportFormat": "lossless",
						"exportQuality": 0.8,
						"fileType": "image/png",
						"imageSpriteId": 9514209,
						"useCollisionPoly": true,
						"duration": 1,
						"tag": ""
					},
					{
						"width": 64,
						"height": 64,
						"originX": 0.5,
						"originY": 0.5,
						"originalSource": "",
						"exportFormat": "lossless",
						"exportQuality": 0.8,
						"fileType": "image/png",
						"imageSpriteId": 722123,
						"useCollisionPoly": true,
						"duration": 1,
						"tag": ""
					},
					{
						"width": 64,
						"height": 64,
						"originX": 0.5,
						"originY": 0.5,
						"originalSource": "",
						"exportFormat": "lossless",
						"exportQuality": 0.8,
						"fileType": "image/png",
						"imageSpriteId": 5983468,
						"useCollisionPoly": true,
						"duration": 1,
						"tag": ""
					},
					{
						"width": 64,
						"height": 64,
						"originX": 0.5,
						"originY": 0.5,
						"originalSource": "",
						"exportFormat": "lossless",
						"exportQuality": 0.8,
						"fileType": "image/png",
						"imageSpriteId": 580426,
						"useCollisionPoly": true,
						"duration": 1,
						"tag": ""
					},
					{
						"width": 64,
						"height": 64,
						"originX": 0.5,
						"originY": 0.5,
						"originalSource": "",
						"exportFormat": "lossless",
						"exportQuality": 0.8,
						"fileType": "image/png",
						"imageSpriteId": 6881853,
						"useCollisionPoly": true,
						"duration": 1,
						"tag": ""
					},
					{
						"width": 64,
						"height": 64,
						"originX": 0.5,
						"originY": 0.5,
						"originalSource": "",
						"exportFormat": "lossless",
						"exportQuality": 0.8,
						"fileType": "image/png",
						"imageSpriteId": 3951315,
						"useCollisionPoly": true,
						"duration": 1,
						"tag": ""
					},
					{
						"width": 64,
						"height": 64,
						"originX": 0.5,
						"originY": 0.5,
						"originalSource": "",
						"exportFormat": "lossless",
						"exportQuality": 0.8,
						"fileType": "image/png",
						"imageSpriteId": 7784881,
						"useCollisionPoly": true,
						"duration": 1,
						"tag": ""
					},
					{
						"width": 64,
						"height": 64,
						"originX": 0.5,
						"originY": 0.5,
						"originalSource": "",
						"exportFormat": "lossless",
						"exportQuality": 0.8,
						"fileType": "image/png",
						"imageSpriteId": 6287415,
						"useCollisionPoly": true,
						"duration": 1,
						"tag": ""
					},
					{
						"width": 64,
						"height": 64,
						"originX": 0.5,
						"originY": 0.5,
						"originalSource": "",
						"exportFormat": "lossless",
						"exportQuality": 0.8,
						"fileType": "image/png",
						"imageSpriteId": 2650749,
						"useCollisionPoly": true,
						"duration": 1,
						"tag": ""
					}
				],
				"sid": 957058169256895,
				"name": "Animation 1",
				"isLooping": false,
				"isPingPong": false,
				"repeatCount": 1,
				"repeatTo": 0,
				"speed": 5
			}
		],
		"subfolders": []
	}
}