{
	"name": "Transition",
	"plugin-id": "Sprite",
	"sid": 595851226075850,
	"isGlobal": false,
	"editorNewInstanceIsReplica": true,
	"instanceVariables": [
		{
			"name": "State",
			"type": "string",
			"desc": "",
			"show": true,
			"sid": 211465222414056
		},
		{
			"name": "Tag",
			"type": "string",
			"desc": "",
			"show": true,
			"sid": 439620894735585
		}
	],
	"behaviorTypes": [],
	"effectTypes": [],
	"animations": {
		"items": [
			{
				"frames": [
					{
						"width": 312,
						"height": 240,
						"originX": 0,
						"originY": 0,
						"originalSource": "",
						"exportFormat": "lossless",
						"exportQuality": 0.8,
						"fileType": "image/png",
						"imageSpriteId": 6324852,
						"useCollisionPoly": true,
						"duration": 1,
						"tag": ""
					},
					{
						"width": 312,
						"height": 240,
						"originX": 0,
						"originY": 0,
						"originalSource": "",
						"exportFormat": "lossless",
						"exportQuality": 0.8,
						"fileType": "image/png",
						"imageSpriteId": 6990251,
						"useCollisionPoly": true,
						"duration": 1,
						"tag": ""
					}
				],
				"sid": 276683123685189,
				"name": "Animation 1",
				"isLooping": false,
				"isPingPong": false,
				"repeatCount": 1,
				"repeatTo": 0,
				"speed": 0
			}
		],
		"subfolders": []
	}
}